{
  "name": "block-explorer.dnp.dappnode.eth",
  "version": "0.0.3",
  "description": "a private, locally-hosted block explorer using your personal node",
  "type": "service",
  "dependencies": {},
  "author": "thenateway",
  "categories": [
    "Developer tools"
  ],
  "links": {
    "ui": "http://block-explorer.dappnode",
    "homepage": "https://github.com/dappnode/DappnodePackage-block-explorer",
    "block-explorer": "https://github.com/Alethio/ethereum-lite-explorer"
  },
  "license": "GLP-3.0"
}
